{
  "pois": [
    {
      "id": "BL",
      "label": "BL",
      "description": "Bottom Left corner of Anchor_Painting_For_Test_World_Coord",
      "blueprint_position": { "x": -0.3, "y": -0.54, "z": 0.44 },
      "icon_name": "BL",
      "nearest_anchor_id": "Anchor_Painting_For_Test_World_Coord"
    },
    {
      "id": "BR",
      "label": "BR",
      "description": "Bottom Right corner of Anchor_Painting_For_Test_World_Coord",
      "blueprint_position": { "x": 0.27, "y": -0.52, "z": -0.39 },
      "icon_name": "BR",
      "nearest_anchor_id": "Anchor_Painting_For_Test_World_Coord"
    },
    {
      "id": "TL",
      "label": "TL",
      "description": "Top Left corner of Anchor_Painting_For_Test_World_Coord",
      "blueprint_position": { "x": -0.3, "y": 0.49, "z": 0.44 },
      "icon_name": "TL",
      "nearest_anchor_id": "Anchor_Painting_For_Test_World_Coord"
    },
    {
      "id": "TR",
      "label": "TR",
      "description": "Top Right corner of Anchor_Painting_For_Test_World_Coord",
      "blueprint_position": { "x": 0.29, "y": 0.48, "z": -0.38 },
      "icon_name": "TR",
      "nearest_anchor_id": "Anchor_Painting_TOP_RIGHT"
    }
  ]
}
